cloe_fabric_connector/__init__.py
cloe_fabric_connector/fabric_connection.py
cloe_fabric_connector/lakehouse_client.py
cloe_fabric_connector/py.typed
cloe_fabric_connector/token_provider.py
cloe_fabric_connector-0.1.1.dist-info/METADATA
cloe_fabric_connector-0.1.1.dist-info/WHEEL
cloe_fabric_connector-0.1.1.dist-info/RECORD
