Metadata-Version: 2.4
Name: cloe-fabric-connector
Version: 0.1.1
Summary: Provides basic interface for connecting to and interacting with a Fabric instance.
Author-email: initions <ICSMC_EXT_PYPIORG@accenture.com>
License: MIT
Classifier: Development Status :: 5 - Production/Stable
Classifier: Environment :: Console
Classifier: Intended Audience :: Developers
Classifier: License :: OSI Approved :: MIT License
Classifier: Operating System :: OS Independent
Classifier: Programming Language :: Python :: 3
Classifier: Topic :: Database
Requires-Python: <3.14,>=3.12
Requires-Dist: cloe-logging~=0.3.7
Requires-Dist: cloe-metadata~=2.2.4
Requires-Dist: databricks-sdk>=0.20.0
Requires-Dist: httpx>=0.28.1
Requires-Dist: msal~=1.32.3
Requires-Dist: pydantic~=2.10
Requires-Dist: typer~=0.15
